nytimes_scraper/__init__.py
nytimes_scraper/__main__.py
nytimes_scraper/scraper.py
nytimes_scraper/articles/__init__.py
nytimes_scraper/articles/postprocessing.py
nytimes_scraper/articles/scraper.py
nytimes_scraper/comments/__init__.py
nytimes_scraper/comments/postprocessing.py
nytimes_scraper/comments/scraper.py
nytimes_scraper/comments/util.py
nytimes_scraper/nyt_api/__init__.py
nytimes_scraper/nyt_api/api.py
nytimes_scraper/nyt_api/archive.py
nytimes_scraper/nyt_api/community.py
nytimes_scraper-1.1.2.dist-info/METADATA
nytimes_scraper-1.1.2.dist-info/WHEEL
nytimes_scraper-1.1.2.dist-info/top_level.txt
nytimes_scraper-1.1.2.dist-info/RECORD
