Metadata-Version: 2.1
Name: nytimes-scraper
Version: 1.1.2
Summary: Scrape article metadata and comments from NYTimes
Home-page: https://github.com/ietz/nytimes-scraper
Author: Tim Pietz
Author-email: tim@pietz.me
License: MIT
Platform: UNKNOWN
Classifier: License :: OSI Approved :: MIT License
Classifier: Programming Language :: Python :: 3
Classifier: Programming Language :: Python :: 3.8
Requires-Dist: cssselect
Requires-Dist: fire
Requires-Dist: lxml
Requires-Dist: pandas
Requires-Dist: requests
Requires-Dist: tqdm
